{
    "fields": [
                {"name": "email_address", "type": "STRING", "nullable": true},
                {"name": "PersNo", "type": "STRING", "nullable": true},
                {"name": "Firstname", "type": "STRING", "nullable": true},
                {"name": "Lastname", "type": "STRING", "nullable": true},
                {"name": "EmployeeNo", "type": "STRING", "nullable": true},
                {"name": "CoCd", "type": "STRING", "nullable": true},
                {"name": "CompanyCode", "type": "STRING", "nullable": true},
                {"name": "PA", "type": "STRING", "nullable": true},
                {"name": "PersonnelArea", "type": "STRING", "nullable": true},
                {"name": "PSubarea", "type": "STRING", "nullable": true},
                {"name": "PersonnelSubarea", "type": "STRING", "nullable": true},
                {"name": "Orgunit", "type": "STRING", "nullable": true},
                {"name": "OrganizationalUnit", "type": "STRING", "nullable": true},
                {"name": "Organizationalkey", "type": "STRING", "nullable": true},
                {"name": "OrganizationalKey1", "type": "STRING", "nullable": true},
                {"name": "WorkC", "type": "STRING", "nullable": true},
                {"name": "WorkContract", "type": "STRING", "nullable": true},
                {"name": "CT", "type": "STRING", "nullable": true},
                {"name": "ContractType", "type": "STRING", "nullable": true},
                {"name": "PSgroup", "type": "STRING", "nullable": true},
                {"name": "PayBandDescription", "type": "STRING", "nullable": true},
                {"name": "FTE", "type": "DOUBLE", "nullable": true},
                {"name": "Wkhrs", "type": "DOUBLE", "nullable": true},
                {"name": "IndicatorPartTimeEmployee", "type": "STRING", "nullable": true},
                {"name": "S", "type": "STRING", "nullable": true},
                {"name": "EmploymentStatus", "type": "STRING", "nullable": true},
                {"name": "GenderKey", "type": "STRING", "nullable": true},
                {"name": "TRAStartDate", "type": "STRING", "nullable": true},
                {"name": "TRAEndDate", "type": "STRING", "nullable": true},
                {"name": "TRAStatus", "type": "STRING", "nullable": true},
                {"name": "TRAGrade", "type": "STRING", "nullable": true},
                {"name": "PrevPersNo", "type": "STRING", "nullable": true},
                {"name": "ActR", "type": "STRING", "nullable": true},
                {"name": "ReasonforAction", "type": "STRING", "nullable": true},
                {"name": "Position", "type": "STRING", "nullable": true},
                {"name": "Position1", "type": "STRING", "nullable": true},
                {"name": "CostCtr", "type": "STRING", "nullable": true},
                {"name": "CostCentre", "type": "STRING", "nullable": true},
                {"name": "CivilServiceStart", "type": "date", "nullable": true},
                {"name": "DatetoCurrentJob", "type": "STRING", "nullable": true},
                {"name": "SeniorityDate", "type": "STRING", "nullable": true},
                {"name": "DatetoSubstGrade", "type": "date", "nullable": true},
                {"name": "PersNo1", "type": "STRING", "nullable": true},
                {"name": "NameofManagerOM", "type": "STRING", "nullable": true},
                {"name": "ManagerPosition", "type": "STRING", "nullable": true},
                {"name": "ManagerPositionText", "type": "STRING", "nullable": true},
                {"name": "CounterSignManager", "type": "STRING", "nullable": true},
                {"name": "Loc", "type": "STRING", "nullable": true},
                {"name": "Location", "type": "STRING", "nullable": true},
                {"name": "OrgStartDate", "type": "date", "nullable": true},
                {"name": "FixTermEndDate", "type": "STRING", "nullable": true},
                {"name": "LoanStartDate", "type": "STRING", "nullable": true},
                {"name": "LoanEndDate", "type": "STRING", "nullable": true},
                {"name": "EEGrp", "type": "STRING", "nullable": true},
                {"name": "EmployeeGroup", "type": "STRING", "nullable": true},
                {"name": "Annualsalary", "type": "STRING", "nullable": true},
                {"name": "Curr", "type": "STRING", "nullable": true},
                {"name": "NInumber", "type": "STRING", "nullable": true},
                {"name": "Birthdate", "type": "STRING", "nullable": true},
                {"name": "Ageofemployee", "type": "STRING", "nullable": true},
                {"name": "EO", "type": "STRING", "nullable": true},
                {"name": "Ethnicorigin", "type": "STRING", "nullable": true},
                {"name": "NID", "type": "STRING", "nullable": true},
                {"name": "Rel", "type": "STRING", "nullable": true},
                {"name": "ReligiousDenominationKey", "type": "STRING", "nullable": true},
                {"name": "SxO", "type": "STRING", "nullable": true},
                {"name": "WageType", "type": "STRING", "nullable": true},
                {"name": "EmployeeSubgroup", "type": "STRING", "nullable": true},
                {"name": "LOAAbsType", "type": "STRING", "nullable": true},
                {"name": "LOAAbsenceTypeText", "type": "STRING", "nullable": true},
                {"name": "Schemereference", "type": "STRING", "nullable": true},
                {"name": "PensionSchemeName", "type": "STRING", "nullable": true},
                {"name": "DisabilityCode", "type": "STRING", "nullable": true},
                {"name": "DisabilityText", "type": "STRING", "nullable": true},
                {"name": "DisabilityCodeDescription", "type": "STRING", "nullable": true},
                {"name": "PArea", "type": "STRING", "nullable": true},
                {"name": "PayrollArea", "type": "STRING", "nullable": true},
                {"name": "AssignmentNumber", "type": "STRING", "nullable": true},
                {"name": "FTE2", "type": "DOUBLE", "nullable": true},
                {"name": "Report_MonthEnd_Date", "type": "DATE", "nullable": true},
				{"name": "PDAC_ETL_Date", "type": "DATE", "nullable": true},				
				{"name": "SourceSystemID", "type": "string","constraints": false},
				{"name": "IngestionDate","type": "timestamp","constraints": false},
				{"name": "ValidTo","type": "timestamp","constraints": false},
				{"name": "RowID","type": "string","constraints": false},
				{"name": "IsActive","type": "string","constraints": false}			
    ]
}
